DayOfWeek/WeekDay.py
DayOfWeek/__init__.py
DayOfWeek-0.0.7.dist-info/LICENSE
DayOfWeek-0.0.7.dist-info/METADATA
DayOfWeek-0.0.7.dist-info/WHEEL
DayOfWeek-0.0.7.dist-info/top_level.txt
DayOfWeek-0.0.7.dist-info/RECORD
