Metadata-Version: 2.1
Name: DayOfWeek
Version: 0.0.7
Summary: My First Python Package
Home-page: UNKNOWN
Author: PythonIsALongTimeFriend
Author-email: kantonato12@gmail.com
License: UNKNOWN
Platform: UNKNOWN
Classifier: Programming Language :: Python :: 3
Classifier: License :: OSI Approved :: MIT License
Classifier: Operating System :: OS Independent
Requires-Python: >=3.6
License-File: LICENSE
